planet_harmonica-0.1.1.dist-info/LICENSE
planet_harmonica-0.1.1.dist-info/METADATA
planet_harmonica-0.1.1.dist-info/RECORD
planet_harmonica-0.1.1.dist-info/top_level.txt
planet_harmonica-0.1.1.dist-info/WHEEL
harmonica/api.py
harmonica/__init__.py
harmonica/bindings.cpython-311-x86_64-linux-gnu.so
harmonica/jax/custom_primitives.py
harmonica/jax/__init__.py
